pyspace/__init__.py
pyspace/data/__init__.py
pyspace/data/analyse.py
pyspace/data/metrics.py
pyspace/data/test.py
pyspace/data_analysis/__init__.py
pyspace/deeplearning/__init__.py
pyspace/deeplearning/keras/__init__.py
pyspace/deeplearning/keras/callback/__init__.py
pyspace/deeplearning/keras/callback/checkpoint.py
pyspace/deeplearning/keras/callback/earlystop.py
pyspace/deeplearning/keras/callback/learningrate.py
pyspace/deeplearning/keras/callback/tensorboard.py
pyspace/deeplearning/keras/loss/__init__.py
pyspace/deeplearning/keras/model/__init__.py
pyspace/deeplearning/pytorch/__init__.py
pyspace/metrics/__init__.py
pyspace/metrics/confusion_functions.py
pyspace/metrics/score_functions.py
pyspace/nlp/__init__.py
pyspace/nlp/dataset/__init__.py
pyspace/nlp/dataset/alignment.py
pyspace/nlp/dataset/load_data.py
pyspace/nlp/models/__init__.py
pyspace/nlp/models/text_gcn/__init__.py
pyspace/nlp/models/text_gcn/__not_working__text_gcn_extended.py
pyspace/nlp/models/text_gcn/fast_text_gcn.py
pyspace/nlp/models/text_gcn/fast_text_gcn_norank.py
pyspace/nlp/models/text_gcn/text_gcn.py
pyspace/nlp/models/text_gcn/text_gtn.py
pyspace/nlp/preprocessing/__init__.py
pyspace/nlp/preprocessing/embedding/__init__.py
pyspace/nlp/preprocessing/normalizer/__init__.py
pyspace/nlp/preprocessing/normalizer/xnormalizer.py
pyspace/nlp/preprocessing/tokenizer/__init__.py
pyspace/nlp/preprocessing/tokenizer/xberttokenizer.py
pyspace/nlp/preprocessing/tokenizer/xspacytokenizer.py
pyspace/nlp/preprocessing/vectorizer/__init__.py
pyspace/nlp/preprocessing/vectorizer/xbertindexer.py
pyspace/nlp/preprocessing/vectorizer/xindexer.py
pyspace/nlp/preprocessing/vectorizer/xpadder.py
pyspace/nlp/task/__init__.py
pyspace/nlp/task/date_extractor.py
pyspace/nlp/task/xbeneparconstituency.py
pyspace/nlp/task/xhasimmorphoglogy.py
pyspace/nlp/task/xspacy.py
pyspace/nlp/task/xtrmorphmorphoglogy.py
pyspace/nlp/toolkit/__init__.py
pyspace/nlp/toolkit/spacy.py
pyspace/nlp/toolkit/zemberek.py
pyspace_toolkit-1.1.25.294.dist-info/LICENSE
pyspace_toolkit-1.1.25.294.dist-info/METADATA
pyspace_toolkit-1.1.25.294.dist-info/WHEEL
pyspace_toolkit-1.1.25.294.dist-info/top_level.txt
pyspace_toolkit-1.1.25.294.dist-info/RECORD
