Metadata-Version: 2.1
Name: pyspace-toolkit
Version: 1.1.25.294
Summary: pyspace is a tool set of data science python functions
Home-page: UNKNOWN
Author: Sahin Batmaz
Author-email: sahin.batmaz@gmail.com
License: UNKNOWN
Platform: UNKNOWN
Classifier: Programming Language :: Python :: 3
Classifier: License :: OSI Approved :: MIT License
Classifier: Operating System :: OS Independent
Requires-Python: >=3.6
License-File: LICENSE
Requires-Dist: fuzzywuzzy
Requires-Dist: jellyfish (>=0.8.2)
Requires-Dist: jsonlines
Requires-Dist: JPype1
Requires-Dist: MiniSom
